{
  "schema_version": "2.0",
  "date": "2026-06-01",
  "market": "CN-A",
  "summary": "电力主线在拥挤状态下进入高位强分歧，资金向容量核心和低位补位集中；AI业绩链仅局部修复，科技高位兑现仍未结束。次日默认按结构性震荡处理，并依据电力承接与科技负反馈切换到修复或退潮剧本。",
  "themes": [
    "电力电网",
    "算电协同",
    "AI业绩链",
    "高位兑现"
  ],
  "performance": [
    {
      "name": "华能国际",
      "value": 10.03,
      "unit": "%",
      "note": "电力容量分歧承接，主力净流入约2.67亿元"
    },
    {
      "name": "天孚通信",
      "value": -5.78,
      "unit": "%",
      "note": "科技容量风险锚走弱，主力净流出约17.93亿元"
    },
    {
      "name": "东山精密",
      "value": -10.0,
      "unit": "%",
      "note": "PCB高位兑现，主力净流出约34.93亿元"
    }
  ],
  "watchlist": [
    {
      "symbol": "600011.SH",
      "name": "华能国际",
      "thesis": "电力容量承接锚",
      "trigger": "分歧后快速回收并维持承接",
      "risk": "与粤电力A同步补跌"
    },
    {
      "symbol": "601138.SH",
      "name": "工业富联",
      "thesis": "AI容量修复锚",
      "trigger": "重新站稳75.20",
      "risk": "跌破72.19"
    },
    {
      "symbol": "300394.SZ",
      "name": "天孚通信",
      "thesis": "科技高位风险锚",
      "trigger": "收回440并停止创新低",
      "risk": "继续创新低并扩散负反馈"
    },
    {
      "symbol": "002384.SZ",
      "name": "东山精密",
      "thesis": "PCB高位兑现风险锚",
      "trigger": "跌停反馈收敛",
      "risk": "继续跌停或带动高位容量补跌"
    }
  ],
  "risks": [
    "电力高位分歧扩散为补跌",
    "科技容量风险偏好继续下降",
    "将龙虎榜大额净买误判为止跌确认"
  ],
  "actions": [
    "默认按结构性震荡处理",
    "只做分歧后容量确认",
    "若电力承接失败且科技负反馈扩散，压缩至1成以内或观望"
  ],
  "next_day_plan": {
    "bias": "neutral",
    "focus": [
      "华能国际与粤电力A的电力容量承接",
      "工业富联75.20与72.19",
      "天孚通信440及是否继续创新低",
      "东山精密跌停反馈是否扩散"
    ],
    "avoid": [
      "追高标一致加速",
      "追AI后排补涨",
      "依据龙虎榜总额猜测席位性质"
    ],
    "key_levels": [
      "工业富联: 75.20 / 72.19",
      "天孚通信: 440",
      "华能国际与粤电力A: 是否同步补跌"
    ],
    "notes": "Scenario A修复：电力承接保留且科技负反馈收敛。Scenario B震荡：主线核心筛选延续。Scenario C退潮：电力承接失败且科技跌停负反馈扩散。"
  },
  "metrics": {
    "data_date": "2026-06-01",
    "lhb_read": true,
    "scout_report_available": false,
    "quant_1000_report_available": false,
    "intraday_review_available": false
  },
  "tags": [
    "拥挤主线分歧筛选",
    "价格强资金分歧",
    "龙虎榜总额不等于席位归因"
  ],
  "meta": {
    "author": "Replay",
    "source": "multica-replay"
  }
}
